headpy/__init__.py
headpy/auth.py
headpy/vacancies.py
headpy-0.0.1.dist-info/LICENSE
headpy-0.0.1.dist-info/METADATA
headpy-0.0.1.dist-info/WHEEL
headpy-0.0.1.dist-info/top_level.txt
headpy-0.0.1.dist-info/RECORD
