Metadata-Version: 2.1
Name: headpy
Version: 0.0.1
Summary: A tiny wrapper of app auth and vacancy search on hh.ru API
Home-page: https://github.com/retardigrade/headpy
Author: Petr Martynenko
Author-email: petr.martynenko@gmail.com
License: UNKNOWN
Project-URL: Bug Tracker, https://github.com/retardigrade/headpy/issues
Platform: UNKNOWN
Classifier: Programming Language :: Python :: 3
Classifier: License :: OSI Approved :: MIT License
Classifier: Operating System :: OS Independent
Requires-Python: >=3.6
Requires-Dist: requests
Requires-Dist: tqdm
